{
  "applinks": {
    "details": [
      {
        "appIDs": ["JSB9MC4M42.com.vlatua.app"],
        "components": [
          {
            "/": "/link/*",
            "comment": "Matches any URL with a path that starts with /link/."
          },
          {
            "/": "/*",
            "comment": "Matches any URL with a path that starts with all."
          }
        ]
      }
    ]
  },
  "webcredentials": {
    "apps": ["JSB9MC4M42.com.vlatua.app"]
  },
  "appclips": {
    "apps": ["JSB9MC4M42.com.vlatua.app.Clip"]
  }
}
